whitening/__init__.py
whitening/__main__.py
whitening-0.1.dist-info/METADATA
whitening-0.1.dist-info/WHEEL
whitening-0.1.dist-info/entry_points.txt
whitening-0.1.dist-info/top_level.txt
whitening-0.1.dist-info/RECORD
