Metadata-Version: 2.1
Name: whitening
Version: 0.1
Summary: Document whitening (foreground separation)
Home-page: https://github.com/rossumai/whitening
Author: Bohumir Zamecnik
Author-email: bohumir.zamecnik@gmail.com
License: MIT
Platform: UNKNOWN
Classifier: Development Status :: 3 - Alpha
Classifier: Intended Audience :: Developers
Classifier: Intended Audience :: Science/Research
Classifier: License :: OSI Approved :: MIT License
Classifier: Programming Language :: Python :: 3
Classifier: Programming Language :: Python :: 3.7
Classifier: Operating System :: POSIX :: Linux
Requires-Dist: numpy
Requires-Dist: Pillow
Requires-Dist: scikit-image
Requires-Dist: scipy
Provides-Extra: test
Requires-Dist: pytest ; extra == 'test'
